Workbook

Sheet Epics
A1: SUPER RESERVATION PLATFORM — Epic Backlog
A2: Epic ID | B2: Epic Name | C2: Description | D2: Category | E2: Priority | F2: Phase | G2: Status | H2: # Stories | I2: Story Points Est. | J2: Dependencies | K2: Notes
A3: EP-01 | B3: Authentication & User Management | C3: Consumer registration (phone OTP, social login), business owner login, profile setup, session management. | D3: Foundation | E3: P0 — Must Have | F3: Phase 1 | G3: Backlog | H3: 8 | I3: 21 | J3: — | K3: Blocks all other epics. Must ship first.
A4: EP-02 | B4: Discovery & Search | C4: Consumer browses and searches businesses by category, district, date, party size. Filters, ranking algorithm, business profile display. | D4: Consumer App | E4: P0 — Must Have | F4: Phase 1 | G4: Backlog | H4: 10 | I4: 34 | J4: EP-01 | K4: Ranking algo needs real data to tune. Launch with proximity + rating.
A5: EP-03 | B5: Booking Engine | C5: Core slot availability, tailored category journeys (restaurant, salon), slot hold (Redis), booking state machine, conflict detection, reschedule, cancel. | D5: Core Platform | E5: P0 — Must Have | F5: Phase 1 | G5: Backlog | H5: 14 | I5: 55 | J5: EP-01,EP-02 | K5: Most complex epic. Redis slot locking is critical path.
A6: EP-04 | B6: Payment & Escrow | C6: Paymob integration (card, InstaPay, Fawry, Vodafone Cash, Meeza), deposit capture, escrow, payout, refunds, receipts. | D6: Core Platform | E6: P0 — Must Have | F6: Phase 1 | G6: Backlog | H6: 9 | I6: 34 | J6: EP-03 | K6: WABA registration runs in parallel. Paymob sandbox from Day 1.
A7: EP-05 | B7: No-Show & Cancellation | C7: No-show detection job (every 15 min), penalty split (75/25), card-on-file, dispute window, ops resolution flow. | D7: Core Platform | E7: P0 — Must Have | F7: Phase 1 | G7: Backlog | H7: 7 | I7: 26 | J7: EP-03,EP-04 | K7: Detection job is cron on ECS. Dispute flow needs admin console.
A8: EP-06 | B8: Notifications | C8: WhatsApp Business API (360dialog), SMS fallback (Twilio), push (FCM), booking confirmation, reminders (24h+2h), review prompt, no-show alerts. | D8: Platform | E8: P0 — Must Have | F8: Phase 1 | G8: Backlog | H8: 8 | I8: 21 | J8: EP-03,EP-04,EP-05 | K8: WABA template approval: submit at Week 1. 2–4 week approval time.
A9: EP-07 | B9: Business Dashboard | C9: Business owner web PWA: calendar view, booking management, availability setup, deposit/policy config, staff management (salon), analytics, manual bookings. | D9: Business App | E9: P0 — Must Have | F9: Phase 1 | G9: Backlog | H9: 12 | I9: 55 | J9: EP-01,EP-03,EP-04 | K9: Tablet-first PWA. RTL sidebar on right.
A10: EP-08 | B10: Consumer Mobile App | C10: React Native iOS + Android app: home feed, search, booking journeys, my bookings, profile, settings, RTL Arabic-first UI. | D10: Consumer App | E10: P0 — Must Have | F10: Phase 1 | G10: Backlog | H10: 10 | I10: 42 | J10: EP-01,EP-02,EP-03,EP-04,EP-06 | K10: App Store + Play Store submission: allow 2 weeks before launch.
A11: EP-09 | B11: Admin Console | C11: Internal ops tool: business verification, dispute resolution, platform health dashboard, featured listing management, refund execution, user management. | D11: Internal | E11: P0 — Must Have | F11: Phase 1 | G11: Backlog | H11: 8 | I11: 26 | J11: EP-01,EP-03,EP-04,EP-05 | K11: Internal web app. No App Store. Ops team uses from Day 1.
A12: EP-10 | B12: Reviews & Loyalty (Phase 1 Foundation) | C12: Post-visit review prompt (WhatsApp), verified-booker-only reviews, moderation queue, rating display on profile. Loyalty points as placeholder schema only. | D12: Consumer App | E12: P1 — Should Have | F12: Phase 1 | G12: Backlog | H12: 6 | I12: 18 | J12: EP-03,EP-06 | K12: Full loyalty program (cross-category points) is Phase 2.
A13: EP-11 | B13: Sports Court Booking | C13: Court category journey: sport type, duration, slot, player count, equipment rental, squad share card. Business config: court inventory, hourly pricing. | D13: Consumer App | E13: P1 — Should Have | F13: Phase 2 | G13: Backlog | H13: 8 | I13: 26 | J13: EP-03,EP-07 | K13: Phase 2. Court booking engine extends core EP-03 with duration slots.
A14: EP-12 | B14: Gaming Cafe Booking | C14: Gaming cafe category: station type (PC/console/VR), duration, group room, genre preference. Business config: station inventory, block durations. | D14: Consumer App | E14: P1 — Should Have | F14: Phase 2 | G14: Backlog | H14: 7 | I14: 21 | J14: EP-03,EP-07 | K14: Phase 2. Similar slot logic to courts.
... A20: EP-18 | B20: Data Intelligence API | C20: Booking density heatmaps, demand intelligence reports for prop-tech clients (ODH, Beltone KEE). API layer with commercial licensing. | D20: Platform | E20: P2 — Nice to Have | F20: Phase 3 | G20: Backlog | H20: 4 | I20: 18 | J20: EP-03 | K20: Phase 3. Requires 100K+ monthly bookings to be commercially valuable.
A21: TOTALS | H21: 142 | I21: 509

Sheet User Stories
A1: SUPER RESERVATION PLATFORM — User Story Backlog
A2: Story ID | B2: Epic ID | C2: Role | D2: User Story | E2: Acceptance Criteria | F2: Priority | G2: Phase | H2: Status | I2: Story Points | J2: Category | K2: Screen / Component | L2: Dependencies | M2: Notes | N2: Labels
A3: US-001 | B3: EP-01 | C3: Consumer | D3: As a consumer, I want to register with my Egyptian phone number so I can create an account without an email. | E3: 1. OTP sent to +20 mobile within 5 seconds. 2. OTP expires in 5 minutes. 3. 5 failed attempts trigger 15-min lockout. 4. Phone number stored in E.164 format. 5. Success redirects to profile setup. | F3: P0 — Must Have | G3: Phase 1 | H3: Backlog | I3: 3 | J3: Auth | K3: Registration Screen | L3: — | M3: Phone must accept +20 prefix. Also international. | N3: auth,consumer,registration
A4: US-002 | B4: EP-01 | C4: Consumer | D4: As a consumer, I want to sign in with Google or Apple so I can log in without entering a phone number. | E4: 1. Apple Sign-In shown on iOS (App Store requirement). 2. Google shown on both iOS and Android. 3. First login creates account; repeat login signs in. 4. Social login fetches display name and email. 5. Arabic UI throughout flow. | F4: P0 — Must Have | G4: Phase 1 | H4: Backlog | I4: 3 | J4: Auth | K4: Login Screen | L4: — | M4: Apple Sign-In is mandatory for iOS App Store compliance. | N4: auth,consumer,social-login
A5: US-003 | B5: EP-01 | C5: Consumer | D5: As a consumer, I want to set up my profile (name, language, notification preferences) so the app is personalised for me. | E5: 1. Name field: Arabic or Latin, required. 2. Language toggle: Arabic (default) / English. 3. Notification preferences: WhatsApp on/off, push on/off. 4. Profile photo optional (S3 upload). 5. Saved and shown in profile tab. | F5: P1 — Should Have | G5: Phase 1 | H5: Backlog | I5: 2 | J5: Auth | K5: Profile Setup Screen | L5: US-001 | M5: Language preference drives all subsequent UI and notification language. | N5: auth,consumer,profile
A6: US-004 | B6: EP-01 | C6: Business Owner | D6: As a business owner, I want to log in with my phone number or email so I can access my dashboard securely. | E6: 1. Phone OTP login: same flow as consumer. 2. Email + password login: email verified on first setup. 3. Session persists 30 days on trusted device. 4. Password reset via SMS OTP. 5. Dashboard shown immediately after login. | F6: P0 — Must Have | G6: Phase 1 | H6: Backlog | I6: 2 | J6: Auth | K6: Business Login Screen | L6: — | M6: Separate from consumer login UI but shared backend auth service. | N6: auth,business,login
A7: US-005 | B7: EP-01 | C7: Business Owner | D7: As a business owner, I want to set up my business profile (name, location, photos, description) so customers can find and trust my business. | E7: 1. Name required in Arabic AND English. 2. Min 3 photos uploaded (S3). 3. Location: address text + Google Maps pin confirmation. 4. Category selection: restaurant/salon/court/gaming/carwash. 5. Profile saved with status PENDING (awaiting ops verification). | F7: P0 — Must Have | G7: Phase 1 | H7: Backlog | I7: 3 | J7: Auth | K7: Business Profile Setup | L7: US-004 | M7: Ops must verify before profile goes ACTIVE. SLA: 24 hours. | N7: auth,business,profile,onboarding
A8: US-006 | B8: EP-01 | C8: Consumer | D8: As a logged-in consumer, I want to log out from any device so I can secure my account. | E8: 1. Logout clears JWT and refresh token. 2. Session invalidated server-side. 3. Redirect to login screen. 4. Push notification token deregistered on logout. | F8: P1 — Should Have | G8: Phase 1 | H8: Backlog | I8: 1 | J8: Auth | K8: Profile / Settings Screen | L8: US-001 | M8: Standard auth flow. | N8: auth,consumer,security
A9: US-007 | B9: EP-01 | C9: Admin | D9: As an ops admin, I want to verify a newly registered business within 24 hours so only real businesses appear on the platform. | E9: 1. New businesses appear in PENDING queue in admin console. 2. Ops can view: name, category, location, photos, phone. 3. Approve: status → ACTIVE, WhatsApp notification sent to owner. 4. Reject: reason required, WhatsApp notification with reason sent. 5. SLA alert if business pending > 24 hours. | F9: P0 — Must Have | G9: Phase 1 | H9: Backlog | I9: 3 | J9: Admin | K9: Admin — Business Verification | L9: US-005,EP-09 | M9: Core trust and safety gate. No business auto-activates. | N9: auth,admin,verification,trust
A10: US-008 | B10: EP-01 | C10: Consumer | D10: As a returning consumer, I want to reset my password via SMS OTP so I can regain access to my account. | E10: 1. 'Forgot password' on login screen. 2. OTP sent to registered phone. 3. OTP valid 5 minutes. 4. New password set: minimum 8 characters. 5. All existing sessions invalidated on reset. | F10: P1 — Should Have | G10: Phase 1 | H10: Backlog | I10: 2 | J10: Auth | K10: Password Reset Screen | L10: US-001 | M10: Standard reset flow. | N10: auth,consumer,security
A11: US-009 | B11: EP-02 | C11: Consumer | D11: As a consumer, I want to see a personalised home feed of businesses near me so I can quickly find something to book. | E11: 1. Home feed shows businesses within 10km sorted by proximity × rating × availability. 2. Category tiles at top: restaurant, salon, court, gaming, car wash. 3. Featured businesses (max 3) shown above organic results. 4. Feed loads within 1.5 seconds on 4G. 5. Skeleton screen shown during load. | F11: P0 — Must Have | G11: Phase 1 | H11: Backlog | I11: 5 | J11: Discovery | K11: Home Screen | L11: US-001 | M11: Featured tile logic linked to EP-17 but feed itself is Phase 1. | N11: discovery,consumer,home-feed
A12: US-010 | B12: EP-02 | C12: Consumer | D12: As a consumer, I want to search for restaurants by name, district, date, and party size so I can find what I need quickly. | E12: 1. Search bar on home and search tab. 2. Auto-complete suggestions after 2 characters. 3. Results filtered by: category, district, date, party size, rating ≥ N. 4. Arabic and transliterated Arabic supported. 5. Empty state with Arabic 'عدّل البحث' CTA shown when no results. | F12: P0 — Must Have | G12: Phase 1 | H12: Backlog | I12: 5 | J12: Discovery | K12: Search Results Screen | L12: US-009 | M12: Arabic full-text search using PostgreSQL tsvector or Elasticsearch. | N12: discovery,consumer,search
A13: US-011 | B13: EP-02 | C13: Consumer | D13: As a consumer, I want to view a business profile with photos, rating, menu/services, and available slots so I can decide whether to book. | E13: 1. Profile shows: photos (min 3, lazy loaded), name AR+EN, description AR+EN, rating (after ≥5 reviews), review count, location map, services list with prices. 2. Next 3 available slots shown without entering booking flow. 3. 'Book Now' sticky CTA at bottom. 4. Map link opens Google Maps. | F13: P0 — Must Have | G13: Phase 1 | H13: Backlog | I13: 5 | J13: Discovery | K13: Business Profile Screen | L13: US-009,US-010 | M13: Star rating shown only after 5 reviews — display 'New' badge before that. | N13: discovery,consumer,profile
A14: US-012 | B14: EP-02 | C14: Consumer | D14: As a consumer, I want to filter search results by cuisine type, section, and rating so I can narrow down my options. | E14: 1. Filter panel: cuisine type (restaurants), service type (salons), rating (≥3/4/5), price range, indoor/outdoor. 2. Filters persist during session. 3. Active filter count badge shown on filter button. 4. Clear all filters with one tap. 5. Results refresh without full page reload. | F14: P1 — Should Have | G14: Phase 1 | H14: Backlog | I14: 3 | J14: Discovery | K14: Search Results — Filter Panel | L14: US-010 | M14: Max 6 simultaneous filters. | N14: discovery,consumer,filters
... A82: US-080 | B82: EP-10 | C82: Consumer | D82: As a consumer, I want a 'Book Again' shortcut on my completed booking so I can rebook a place I liked in one tap. | E82: 1. After review prompt (or 2h post-visit), 'Book Again' CTA shown in app. 2. Tapping pre-fills booking journey with same business. 3. Previous booking preferences pre-populated: party size, occasion. 4. Consumer still selects new date/time. 5. Also visible on past bookings list. | F82: P1 — Should Have | G82: Phase 1 | H82: Backlog | I82: 2 | J82: Reviews | K82: Past Bookings — Book Again | L82: US-026,US-075 | M82: Highest-ROI retention mechanic. Requires completed booking history. | N82: reviews,consumer,retention,rebook

Sheet Sprint Plan
A1: SUPER RESERVATION PLATFORM — Phase 1 Sprint Plan
A2: Sprint | B2: Duration | C2: Theme | D2: Stories Included | E2: Story Points | F2: Goal | G2: Dependencies | H2: Notes
A3: Sprint 0 | B3: 2 weeks | C3: Infrastructure & Setup | D3: US-001, US-002, US-004, US-005 (partial) | E3: 10 | F3: Cloud infra on AWS me-south-1. CI/CD pipeline. DB schema. Paymob sandbox. WABA registration initiated. Auth flows complete. | G3: — | H3: Submit WABA templates to Meta in Week 1. Start WABA approval clock.
A4: Sprint 1 | B4: 2 weeks | C4: Core Auth + Business Profile | D4: US-003, US-005, US-006, US-007, US-008 | E4: 11 | F4: Full auth for consumer and business. Business profile setup. Ops verification flow live. Business can go through onboarding end-to-end. | G4: Sprint 0 | H4: Ops team must be trained on verification console before Sprint 1 ends.
A5: Sprint 2 | B5: 2 weeks | C5: Discovery & Search | D5: US-009, US-010, US-011, US-012, US-014 | E5: 18 | F5: Consumer can search, filter, and view business profiles. Ranking algorithm live. Arabic RTL search results. Home feed with category tiles. | G5: Sprint 1 | H5: Real data needed for algorithm tuning. Use seed data in staging.
A6: Sprint 3 | B6: 2 weeks | C6: Booking Engine — Core | D6: US-016, US-017, US-019, US-020, US-023, US-025 | E6: 22 | F6: Restaurant booking journey fully functional end-to-end. Slot locking (Redis). Booking state machine. Conflict detection. Booking reference generated. | G6: Sprint 2 | H6: Redis deployed in Sprint 0. Booking journey is the most complex sprint — allocate full team.
A7: Sprint 4 | B7: 2 weeks | C7: Payments | D7: US-029, US-030, US-031, US-035, US-037 | E7: 21 | F7: Full payment flow: InstaPay, card, Fawry, Vodafone Cash. Escrow model live. Card-on-file. HMAC webhook security. Platform fee collection. | G7: Sprint 3 | H7: Paymob production account needed by end of Sprint 4. Sandbox used in Sprint 3 testing.
A8: Sprint 5 | B8: 2 weeks | C8: No-Show + Notifications | D8: US-038, US-039, US-040, US-042, US-043, US-044, US-045, US-046, US-050, US-052 | E8: 27 | F8: No-show detection job live. Penalty split automated. Dispute window. WhatsApp confirmations, reminders, no-show alerts. SQS notification queue. | G8: Sprint 4 | H8: WABA templates must be approved by start of Sprint 5. If not: SMS fallback only.
A9: Sprint 6 | B9: 2 weeks | C9: Business Dashboard | D9: US-053, US-054, US-055, US-056, US-057, US-058, US-060, US-062 | E9: 27 | F9: Full business dashboard: calendar, analytics, booking management, availability config, staff management (salon), sections config (restaurant). | G9: Sprint 3,Sprint 4 | H9: Tablet-first PWA. RTL sidebar. Onboarding checklist shipped.
A10: Sprint 7 | B10: 2 weeks | C10: Salon Booking + Consumer App Polish | D10: US-018, US-028, US-063, US-064, US-065, US-066, US-067, US-068 | E10: 29 | F10: Salon booking journey complete. Consumer app Arabic RTL audit. Skeleton screens. Empty states. Device testing (Samsung A54, Xiaomi Redmi Note 12). Apple Sign-In. | G10: Sprint 3,Sprint 6 | H10: Device testing must include physical Egyptian-market devices with Egyptian SIM cards.
A11: Sprint 8 | B11: 2 weeks | C11: Admin Console + Reviews | D11: US-069, US-070, US-071, US-072, US-073, US-075, US-076, US-077, US-079, US-080 | E11: 25 | F11: Admin console: health dashboard, verification queue, dispute resolution, business suspension. Review flow: prompt, submission, moderation, display. Book Again feature. | G11: Sprint 5,Sprint 6 | H11: Admin console is pre-launch critical. Ops team user acceptance test in Sprint 8.
A12: Sprint 9 | B12: 2 weeks | C12: QA, Performance, Launch Prep | D12: All P0 stories regression tested. Load test (100 concurrent bookings). WABA production live. App Store + Play Store submission. Arabic copy final review. | E12: — | F12: Pass all 7 MVP launch gates (see PRD Section 8). Platform ready for soft launch with 20 pilot businesses. | G12: Sprint 0–8 | H12: App Store review: submit 2 weeks early. Allow 1 week for rejection + resubmission.

Sheet Summary
A1: BACKLOG SUMMARY
A3: Metric | B3: Value
A4: Total Epics | B4: =COUNTA(Epics!A3:A100)-1 -> 18
A5: Total User Stories | B5: =COUNTA('User Stories'!A3:A200)-1 -> 79
A6: Total Story Points | B6: =SUM('User Stories'!I3:I200) -> 264
A8: By Priority | B8: Stories | C8: Points
A9: P0 — Must Have | B9: =COUNTIF('User Stories'!F3:F200,"P0 — Must Have") -> 56 | C9: =SUMIF('User Stories'!F3:F200,"P0 — Must Have",'User Stories'!I3:I200) -> 207
A10: P1 — Should Have | B10: =COUNTIF('User Stories'!F3:F200,"P1 — Should Have") -> 22 | C10: =SUMIF('User Stories'!F3:F200,"P1 — Should Have",'User Stories'!I3:I200) -> 50
A11: P2 — Nice to Have | B11: =COUNTIF('User Stories'!F3:F200,"P2 — Nice to Have") -> 2 | C11: =SUMIF('User Stories'!F3:F200,"P2 — Nice to Have",'User Stories'!I3:I200) -> 7
A13: By Phase | B13: Stories | C13: Points
A14: Phase 1 | B14: =COUNTIF('User Stories'!G3:G200,"Phase 1") -> 78 | C14: =SUMIF('User Stories'!G3:G200,"Phase 1",'User Stories'!I3:I200) -> 259
A15: Phase 2 | B15: =COUNTIF('User Stories'!G3:G200,"Phase 2") -> 2 | C15: =SUMIF('User Stories'!G3:G200,"Phase 2",'User Stories'!I3:I200) -> 5
A16: Phase 3 | B16: =COUNTIF('User Stories'!G3:G200,"Phase 3") -> 0 | C16: =SUMIF('User Stories'!G3:G200,"Phase 3",'User Stories'!I3:I200) -> 0
A18: By Epic | B18: Stories | C18: Points
A19: EP-01 | B19: =COUNTIF('User Stories'!B3:B200,"EP-01") -> 8 | C19: =SUMIF('User Stories'!B3:B200,"EP-01",'User Stories'!I3:I200) -> 19
A20: EP-02 | B20: =COUNTIF('User Stories'!B3:B200,"EP-02") -> 7 | C20: =SUMIF('User Stories'!B3:B200,"EP-02",'User Stories'!I3:I200) -> 30
A21: EP-03 | B21: =COUNTIF('User Stories'!B3:B200,"EP-03") -> 13 | C21: =SUMIF('User Stories'!B3:B200,"EP-03",'User Stories'!I3:I200) -> 57
A22: EP-04 | B22: =COUNTIF('User Stories'!B3:B200,"EP-04") -> 9 | C22: =SUMIF('User Stories'!B3:B200,"EP-04",'User Stories'!I3:I200) -> 32
A23: EP-05 | B23: =COUNTIF('User Stories'!B3:B200,"EP-05") -> 7 | C23: =SUMIF('User Stories'!B3:B200,"EP-05",'User Stories'!I3:I200) -> 21
A24: EP-06 | B24: =COUNTIF('User Stories'!B3:B200,"EP-06") -> 8 | C24: =SUMIF('User Stories'!B3:B200,"EP-06",'User Stories'!I3:I200) -> 21
A25: EP-07 | B25: =COUNTIF('User Stories'!B3:B200,"EP-07") -> 10 | C25: =SUMIF('User Stories'!B3:B200,"EP-07",'User Stories'!I3:I200) -> 32
A26: EP-08 | B26: =COUNTIF('User Stories'!B3:B200,"EP-08") -> 6 | C26: =SUMIF('User Stories'!B3:B200,"EP-08",'User Stories'!I3:I200) -> 20
A27: EP-09 | B27: =COUNTIF('User Stories'!B3:B200,"EP-09") -> 6 | C27: =SUMIF('User Stories'!B3:B200,"EP-09",'User Stories'!I3:I200) -> 18
A28: EP-10 | B28: =COUNTIF('User Stories'!B3:B200,"EP-10") -> 6 | C28: =SUMIF('User Stories'!B3:B200,"EP-10",'User Stories'!I3:I200) -> 14
